bbyu/__init__.py
bbyu/generator.py
bbyu/item_type.py
bbyu/data/__init__.py
bbyu/data/korean.py
bbyu_nickname_generator-0.16.dist-info/LICENSE
bbyu_nickname_generator-0.16.dist-info/METADATA
bbyu_nickname_generator-0.16.dist-info/WHEEL
bbyu_nickname_generator-0.16.dist-info/top_level.txt
bbyu_nickname_generator-0.16.dist-info/RECORD
