Metadata-Version: 2.1
Name: bbyu-nickname-generator
Version: 0.16
Summary: bbyu-nickname-generator
Home-page: https://github.com/MartianLee/bbyu-nickname-generator
Author: martianlee
Author-email: martianlee@gmail.com
License: UNKNOWN
Keywords: nickname,name,generator,nickname generator,bbyu
Platform: UNKNOWN
Classifier: Programming Language :: Python :: 3
Classifier: Programming Language :: Python :: 3.2
Classifier: Programming Language :: Python :: 3.3
Classifier: Programming Language :: Python :: 3.4
Classifier: Programming Language :: Python :: 3.5
Classifier: Programming Language :: Python :: 3.6
Classifier: Programming Language :: Python :: 3.7
Requires-Python: >=3
